certmaker/__init__.py
certmaker/_compat.py
certmaker/cli.py
certmaker/config.py
certmaker/constants.py
certmaker/openssl_provider.py
certmaker/pki.py
certmaker/provider.py
certmaker/utils.py
certmaker-0.0.0a0.data/data/CHANGELOG.md
certmaker-0.0.0a0.dist-info/AUTHORS
certmaker-0.0.0a0.dist-info/LICENSE.rst
certmaker-0.0.0a0.dist-info/METADATA
certmaker-0.0.0a0.dist-info/WHEEL
certmaker-0.0.0a0.dist-info/entry_points.txt
certmaker-0.0.0a0.dist-info/top_level.txt
certmaker-0.0.0a0.dist-info/RECORD
