Metadata-Version: 2.1
Name: certmaker
Version: 0.0.0a0
Summary: Binary Data Analyzer
Home-page: https://certmaker.denisvasilik.com
Author: Denis Vasilìk
Author-email: contact@denisvasilik.com
License: UNKNOWN
Project-URL: Bug Tracker, https://github.com/denisvasilik/certmaker/issues/
Project-URL: Documentation, https://certmaker.readthedocs.io/en/latest/
Project-URL: Source Code, https://github.com/denisvasilik/certmaker/
Platform: UNKNOWN
Classifier: Programming Language :: Python :: 3.6
Classifier: Operating System :: POSIX :: Linux
Requires-Dist: certmaker
Requires-Dist: click (>=5.1)
